Workbook

Sheet Margin
A1: Growth scale — 100 companies, per company per month (support costed at the hourly rate on Assumptions)
A2: Plan | B2: Monthly price | C2: Annual, per month | D2: Hosting | E2: Included usage | F2: Included support (cost) | G2: Extra support (revenue) | H2: Extra support (cost) | I2: Onboarding fee (per month) | J2: Onboarding time (cost per month) | K2: Card fees, monthly billing | L2: Card fees, annual billing | M2: Margin, monthly billing | N2: Margin %, monthly | O2: Margin, annual billing | P2: Margin %, annual | Q2: Support hours carried per month
A3: Starter | B3: =Assumptions!$B$3 -> 29 | C3: =B3*Assumptions!$B$30/12 -> 24.166667 | D3: =IF((Assumptions!$B$14+Assumptions!$C$14+Assumptions!$D$14+Assumptions!$E$14)=0,0,Assumptions!$B$17*(Assumptions!$B$18/(Assumptions!$B$14+Assumptions!$C$14+Assumptions!$D$14+Assumptions!$E$14)+(1-Assumptions!$B$18)*Assumptions!$B$4*Assumptions!$B$5/(Assumptions!$B$14*Assumptions!$B$4*Assumptions!$B$5+Assumptions!$C$14*Assumptions!$C$4*Assumptions!$C$5+Assumptions!$D$14*Assumptions!$D$4*Assumptions!$D$5+Assumptions!$E$14*Assumptions!$E$4*Assumptions!$E$5))) -> 7.336918 | E3: =Assumptions!$B$4*Assumptions!$B$5*Assumptions!$B$19/1000*Assumptions!$B$20+Assumptions!$B$4*Assumptions!$B$5*Assumptions!$B$21*Assumptions!$B$22+Assumptions!$B$6*Assumptions!$B$24/1000*Assumptions!$B$23 -> 0.1342 | F3: =MIN(Assumptions!$B$7,Assumptions!$B$8)*Assumptions!$B$25 -> 10 | G3: =MAX(0,Assumptions!$B$8-Assumptions!$B$7)*Assumptions!$B$9*Assumptions!$B$26 -> 6 | H3: =MAX(0,Assumptions!$B$8-Assumptions!$B$7)*Assumptions!$B$9*Assumptions!$B$25 -> 4 | I3: =Assumptions!$B$10*Assumptions!$B$11/Assumptions!$B$27 -> 1.2375 | J3: =(Assumptions!$B$11*Assumptions!$B$12+(1-Assumptions!$B$11)*Assumptions!$B$13)*Assumptions!$B$25/Assumptions!$B$27 -> 1.3333333 | K3: =(B3+G3+I3)*Assumptions!$B$28+Assumptions!$B$29 -> 1.387125 | L3: =(C3*12*Assumptions!$B$28+Assumptions!$B$29)/12+(G3+I3)*Assumptions!$B$28 -> 0.967125 | M3: =B3+G3+I3-D3-E3-F3-H3-J3-K3 -> 12.045924 | N3: =IF(B3+G3+I3=0,0,M3/(B3+G3+I3)) -> 0.33241597 | O3: =C3+G3+I3-D3-E3-F3-H3-J3-L3 -> 7.6325903 | P3: =IF(C3+G3+I3=0,0,O3/(C3+G3+I3)) -> 0.24304387 | Q3: =MIN(Assumptions!$B$7,Assumptions!$B$8)+MAX(0,Assumptions!$B$8-Assumptions!$B$7)*Assumptions!$B$9+(Assumptions!$B$11*Assumptions!$B$12+(1-Assumptions!$B$11)*Assumptions!$B$13)/Assumptions!$B$27 -> 0.38333333
A4: Growth | B4: =Assumptions!$C$3 -> 79 | C4: =B4*Assumptions!$B$30/12 -> 65.833333 | D4: =IF((Assumptions!$B$14+Assumptions!$C$14+Assumptions!$D$14+Assumptions!$E$14)=0,0,Assumptions!$B$17*(Assumptions!$B$18/(Assumptions!$B$14+Assumptions!$C$14+Assumptions!$D$14+Assumptions!$E$14)+(1-Assumptions!$B$18)*Assumptions!$C$4*Assumptions!$C$5/(Assumptions!$B$14*Assumptions!$B$4*Assumptions!$B$5+Assumptions!$C$14*Assumptions!$C$4*Assumptions!$C$5+Assumptions!$D$14*Assumptions!$D$4*Assumptions!$D$5+Assumptions!$E$14*Assumptions!$E$4*Assumptions!$E$5))) -> 13.578393 | E4: =Assumptions!$C$4*Assumptions!$C$5*Assumptions!$B$19/1000*Assumptions!$B$20+Assumptions!$C$4*Assumptions!$C$5*Assumptions!$B$21*Assumptions!$B$22+Assumptions!$C$6*Assumptions!$B$24/1000*Assumptions!$B$23 -> 0.489 | F4: =MIN(Assumptions!$C$7,Assumptions!$C$8)*Assumptions!$B$25 -> 30 | G4: =MAX(0,Assumptions!$C$8-Assumptions!$C$7)*Assumptions!$C$9*Assumptions!$B$26 -> 18 | H4: =MAX(0,Assumptions!$C$8-Assumptions!$C$7)*Assumptions!$C$9*Assumptions!$B$25 -> 12 | I4: =Assumptions!$C$10*Assumptions!$C$11/Assumptions!$B$27 -> 8.2916667 | J4: =(Assumptions!$C$11*Assumptions!$C$12+(1-Assumptions!$C$11)*Assumptions!$C$13)*Assumptions!$B$25/Assumptions!$B$27 -> 5 | K4: =(B4+G4+I4)*Assumptions!$B$28+Assumptions!$B$29 -> 3.45875 | L4: =(C4*12*Assumptions!$B$28+Assumptions!$B$29)/12+(G4+I4)*Assumptions!$B$28 -> 2.78875 | M4: =B4+G4+I4-D4-E4-F4-H4-J4-K4 -> 40.765523 | N4: =IF(B4+G4+I4=0,0,M4/(B4+G4+I4)) -> 0.38716761 | O4: =C4+G4+I4-D4-E4-F4-H4-J4-L4 -> 28.268857 | P4: =IF(C4+G4+I4=0,0,O4/(C4+G4+I4)) -> 0.30685326 | Q4: =MIN(Assumptions!$C$7,Assumptions!$C$8)+MAX(0,Assumptions!$C$8-Assumptions!$C$7)*Assumptions!$C$9+(Assumptions!$C$11*Assumptions!$C$12+(1-Assumptions!$C$11)*Assumptions!$C$13)/Assumptions!$B$27 -> 1.175
A5: Business | B5: =Assumptions!$D$3 -> 199 | C5: =B5*Assumptions!$B$30/12 -> 165.83333 | D5: =IF((Assumptions!$B$14+Assumptions!$C$14+Assumptions!$D$14+Assumptions!$E$14)=0,0,Assumptions!$B$17*(Assumptions!$B$18/(Assumptions!$B$14+Assumptions!$C$14+Assumptions!$D$14+Assumptions!$E$14)+(1-Assumptions!$B$18)*Assumptions!$D$4*Assumptions!$D$5/(Assumptions!$B$14*Assumptions!$B$4*Assumptions!$B$5+Assumptions!$C$14*Assumptions!$C$4*Assumptions!$C$5+Assumptions!$D$14*Assumptions!$D$4*Assumptions!$D$5+Assumptions!$E$14*Assumptions!$E$4*Assumptions!$E$5))) -> 26.952984 | E5: =Assumptions!$D$4*Assumptions!$D$5*Assumptions!$B$19/1000*Assumptions!$B$20+Assumptions!$D$4*Assumptions!$D$5*Assumptions!$B$21*Assumptions!$B$22+Assumptions!$D$6*Assumptions!$B$24/1000*Assumptions!$B$23 -> 1.535 | F5: =MIN(Assumptions!$D$7,Assumptions!$D$8)*Assumptions!$B$25 -> 120 | G5: =MAX(0,Assumptions!$D$8-Assumptions!$D$7)*Assumptions!$D$9*Assumptions!$B$26 -> 0 | H5: =MAX(0,Assumptions!$D$8-Assumptions!$D$7)*Assumptions!$D$9*Assumptions!$B$25 -> 0 | I5: =Assumptions!$D$10*Assumptions!$D$11/Assumptions!$B$27 -> 16.625 | J5: =(Assumptions!$D$11*Assumptions!$D$12+(1-Assumptions!$D$11)*Assumptions!$D$13)*Assumptions!$B$25/Assumptions!$B$27 -> 10 | K5: =(B5+G5+I5)*Assumptions!$B$28+Assumptions!$B$29 -> 6.76875 | L5: =(C5*12*Assumptions!$B$28+Assumptions!$B$29)/12+(G5+I5)*Assumptions!$B$28 -> 5.49875 | M5: =B5+G5+I5-D5-E5-F5-H5-J5-K5 -> 50.368266 | N5: =IF(B5+G5+I5=0,0,M5/(B5+G5+I5)) -> 0.23359196 | O5: =C5+G5+I5-D5-E5-F5-H5-J5-L5 -> 18.4716 | P5: =IF(C5+G5+I5=0,0,O5/(C5+G5+I5)) -> 0.10123736 | Q5: =MIN(Assumptions!$D$7,Assumptions!$D$8)+MAX(0,Assumptions!$D$8-Assumptions!$D$7)*Assumptions!$D$9+(Assumptions!$D$11*Assumptions!$D$12+(1-Assumptions!$D$11)*Assumptions!$D$13)/Assumptions!$B$27 -> 3.25
A6: Enterprise | B6: =Assumptions!$E$3 -> 499 | C6: =B6*Assumptions!$B$30/12 -> 415.83333 | D6: =IF((Assumptions!$B$14+Assumptions!$C$14+Assumptions!$D$14+Assumptions!$E$14)=0,0,Assumptions!$B$17*(Assumptions!$B$18/(Assumptions!$B$14+Assumptions!$C$14+Assumptions!$D$14+Assumptions!$E$14)+(1-Assumptions!$B$18)*Assumptions!$E$4*Assumptions!$E$5/(Assumptions!$B$14*Assumptions!$B$4*Assumptions!$B$5+Assumptions!$C$14*Assumptions!$C$4*Assumptions!$C$5+Assumptions!$D$14*Assumptions!$D$4*Assumptions!$D$5+Assumptions!$E$14*Assumptions!$E$4*Assumptions!$E$5))) -> 49.243967 | E6: =Assumptions!$E$4*Assumptions!$E$5*Assumptions!$B$19/1000*Assumptions!$B$20+Assumptions!$E$4*Assumptions!$E$5*Assumptions!$B$21*Assumptions!$B$22+Assumptions!$E$6*Assumptions!$B$24/1000*Assumptions!$B$23 -> 3.07 | F6: =MIN(Assumptions!$E$7,Assumptions!$E$8)*Assumptions!$B$25 -> 240 | G6: =MAX(0,Assumptions!$E$8-Assumptions!$E$7)*Assumptions!$E$9*Assumptions!$B$26 -> 0 | H6: =MAX(0,Assumptions!$E$8-Assumptions!$E$7)*Assumptions!$E$9*Assumptions!$B$25 -> 0 | I6: =Assumptions!$E$10*Assumptions!$E$11/Assumptions!$B$27 -> 33.291667 | J6: =(Assumptions!$E$11*Assumptions!$E$12+(1-Assumptions!$E$11)*Assumptions!$E$13)*Assumptions!$B$25/Assumptions!$B$27 -> 20 | K6: =(B6+G6+I6)*Assumptions!$B$28+Assumptions!$B$29 -> 16.26875 | L6: =(C6*12*Assumptions!$B$28+Assumptions!$B$29)/12+(G6+I6)*Assumptions!$B$28 -> 13.49875 | M6: =B6+G6+I6-D6-E6-F6-H6-J6-K6 -> 203.70895 | N6: =IF(B6+G6+I6=0,0,M6/(B6+G6+I6)) -> 0.38270174 | O6: =C6+G6+I6-D6-E6-F6-H6-J6-L6 -> 123.31228 | P6: =IF(C6+G6+I6=0,0,O6/(C6+G6+I6)) -> 0.27456116 | Q6: =MIN(Assumptions!$E$7,Assumptions!$E$8)+MAX(0,Assumptions!$E$8-Assumptions!$E$7)*Assumptions!$E$9+(Assumptions!$E$11*Assumptions!$E$12+(1-Assumptions!$E$11)*Assumptions!$E$13)/Assumptions!$B$27 -> 6.5
A7: Whole mix | B7: =Assumptions!$B$14*B3+Assumptions!$C$14*B4+Assumptions!$D$14*B5+Assumptions!$E$14*B6 -> 10400 | C7: =Assumptions!$B$14*C3+Assumptions!$C$14*C4+Assumptions!$D$14*C5+Assumptions!$E$14*C6 -> 8666.6667 | G7: =Assumptions!$B$14*G3+Assumptions!$C$14*G4+Assumptions!$D$14*G5+Assumptions!$E$14*G6 -> 870 | I7: =Assumptions!$B$14*I3+Assumptions!$C$14*I4+Assumptions!$D$14*I5+Assumptions!$E$14*I6 -> 838.66667 | M7: =Assumptions!$B$14*M3+Assumptions!$C$14*M4+Assumptions!$D$14*M5+Assumptions!$E$14*M6 -> 3934.5403 | N7: =IF(B7+G7+I7=0,0,M7/(B7+G7+I7)) -> 0.32493589 | O7: =Assumptions!$B$14*O3+Assumptions!$C$14*O4+Assumptions!$D$14*O5+Assumptions!$E$14*O6 -> 2280.707 | P7: =IF(C7+G7+I7=0,0,O7/(C7+G7+I7)) -> 0.21982012
A8: Whole mix = monthly totals across all 100 companies. Revenue includes extra support and onboarding fees spread over the customer lifetime.
A10: Before and after the rework — annual billing, at the support cost on Assumptions
A11: Plan | B11: Before: all expected support free | C11: Before: margin % | D11: After: margin per month | E11: After: margin % | F11: Change per month
A12: Starter | B12: =C3-D3-E3-Assumptions!$B$8*Assumptions!$B$25-(C3*12*Assumptions!$B$28+Assumptions!$B$29)/12 -> -4.0544514 | C12: =IF(C3=0,0,B12/C3) -> -0.1677704 | D12: =O3 -> 7.6325903 | E12: =P3 -> 0.24304387 | F12: =D12-B12 -> 11.687042
A13: Growth | B13: =C4-D4-E4-Assumptions!$C$8*Assumptions!$B$25-(C4*12*Assumptions!$B$28+Assumptions!$B$29)/12 -> -10.23406 | C13: =IF(C4=0,0,B13/C4) -> -0.15545408 | D13: =O4 -> 28.268857 | E13: =P4 -> 0.30685326 | F13: =D13-B13 -> 38.502917
A14: Business | B14: =C5-D5-E5-Assumptions!$D$8*Assumptions!$B$25-(C5*12*Assumptions!$B$28+Assumptions!$B$29)/12 -> 12.34535 | C14: =IF(C5=0,0,B14/C5) -> 0.07444432 | D14: =O5 -> 18.4716 | E14: =P5 -> 0.10123736 | F14: =D14-B14 -> 6.12625
A15: Enterprise | B15: =C6-D6-E6-Assumptions!$E$8*Assumptions!$B$25-(C6*12*Assumptions!$B$28+Assumptions!$B$29)/12 -> 111.01937 | C15: =IF(C6=0,0,B15/C6) -> 0.26698044 | D15: =O6 -> 123.31228 | E15: =P6 -> 0.27456116 | F15: =D15-B15 -> 12.292917
A18: Annual-billing margin per company per month at different support costs per hour (after the rework)
A19: Plan | B19: $20 / hour | C19: $30 / hour | D19: $40 / hour | E19: $50 / hour | F19: $60 / hour
A20: Starter | B20: =O3+(Assumptions!$B$25-20)*Q3 -> 15.299257 | C20: =O3+(Assumptions!$B$25-30)*Q3 -> 11.465924 | D20: =O3+(Assumptions!$B$25-40)*Q3 -> 7.6325903 | E20: =O3+(Assumptions!$B$25-50)*Q3 -> 3.799257 | F20: =O3+(Assumptions!$B$25-60)*Q3 -> -0.034076366
A21: Growth | B21: =O4+(Assumptions!$B$25-20)*Q4 -> 51.768857 | C21: =O4+(Assumptions!$B$25-30)*Q4 -> 40.018857 | D21: =O4+(Assumptions!$B$25-40)*Q4 -> 28.268857 | E21: =O4+(Assumptions!$B$25-50)*Q4 -> 16.518857 | F21: =O4+(Assumptions!$B$25-60)*Q4 -> 4.7688566
A22: Business | B22: =O5+(Assumptions!$B$25-20)*Q5 -> 83.4716 | C22: =O5+(Assumptions!$B$25-30)*Q5 -> 50.9716 | D22: =O5+(Assumptions!$B$25-40)*Q5 -> 18.4716 | E22: =O5+(Assumptions!$B$25-50)*Q5 -> -14.0284 | F22: =O5+(Assumptions!$B$25-60)*Q5 -> -46.5284
A23: Enterprise | B23: =O6+(Assumptions!$B$25-20)*Q6 -> 253.31228 | C23: =O6+(Assumptions!$B$25-30)*Q6 -> 188.31228 | D23: =O6+(Assumptions!$B$25-40)*Q6 -> 123.31228 | E23: =O6+(Assumptions!$B$25-50)*Q6 -> 58.312283 | F23: =O6+(Assumptions!$B$25-60)*Q6 -> -6.6877172
A24: Extra support is sold at the price on Assumptions ($60 an hour). If support costs rise above that price, extra support no longer covers its own time.

Sheet Read me
A1: ConversaFlow — pricing and support model (draft)
A2: Status: annual pricing approval is on hold (owner, 20 Oct 2026). Nothing here is published or offered.
A4: What changed from the earlier model
A5: • Starter and Growth now include a defined support allowance (15 and 45 minutes a month) instead of absorbing all the support customers ask for.
A6: • Onboarding is paid where it is needed (optional for Starter, included as a fee for Growth and above), and extra support is priced separately per hour.
A7: • Support is costed at $40 an hour (your test value) and a sensitivity table shows $20 to $60.
A8: • The Pilot subsidy sheet shows the total cost of a free pilot for three or five companies and a proposed spending cap.
A10: How to use
A11: • Change only blue numbers (Assumptions and Pilot subsidy). Yellow marks the inputs with the biggest effect.
A12: • Margin compares annual and monthly billing per plan, before and after the rework, and across support costs.
A14: Excluded
A15: • Meta message fees (paid by customers directly), usage overages, AI credits (later phase), sales commission, taxes and development cost.
A16: • Hosting figures are provisional estimates (docs/readiness/hosting-comparison.md); no hosting is selected or bought.

Sheet Assumptions
A1: Assumptions — change only the blue numbers
A2: Per plan | B2: Starter | C2: Growth | D2: Business | E2: Enterprise | F2: Note / source
A3: Monthly price ($) | B3: 29 | C3: 79 | D3: 199 | E3: 499 | F3: BRD v1.1 proposed prices (catalogue version 1)
A4: Seat limit | B4: 3 | C4: 10 | D4: 25 | E4: 50 | F4: BRD v1.1 plan limits
A5: Share of seats in use | B5: 0.7 | C5: 0.7 | D5: 0.7 | E5: 0.7 | F5: Assumption
A6: Included automation runs / month | B6: 1000 | C6: 5000 | D6: 25000 | E6: 50000 | F6: BRD v1.1; Enterprise is custom — 50,000 assumed
A7: Support allowance included (hours / month) | B7: 0.25 | C7: 0.75 | D7: 3 | E7: 6 | F7: Proposed: Starter 15 min (email), Growth 45 min (email and chat); Business and Enterprise unchanged
A8: Support customers expect (hours / month) | B8: 0.5 | C8: 1.5 | D8: 3 | E8: 6 | F8: Same demand as the previous model, so the comparison is fair
A9: Share of time above the allowance bought as extra support | B9: 0.4 | C9: 0.4 | D9: 0.4 | E9: 0.4 | F9: Assumption: the rest is handled by the help centre or not requested
A10: Onboarding fee, one-off ($) | B10: 99 | C10: 199 | D10: 399 | E10: 799 | F10: Proposed: Starter optional assisted set-up; Growth and above include paid onboarding
A11: Share of new companies paying for onboarding | B11: 0.3 | C11: 1 | D11: 1 | E11: 1 | F11: Starter is optional; Growth and above required
A12: Onboarding time when paid (hours) | B12: 1.5 | C12: 3 | D12: 6 | E12: 12 | F12: Assumption: guided set-up call, templates, team and roles
A13: Onboarding time otherwise (hours) | B13: 0.5 | C13: 0.5 | D13: 0 | E13: 0 | F13: Assumption: self-service with one short check-in
A14: Companies at growth scale | B14: 40 | C14: 35 | D14: 20 | E14: 5 | F14: Assumption: plan mix of 100 companies
A16: Shared inputs | B16: Value | F16: Note / source
A17: Hosting at growth scale ($ / month) | B17: 1554 | F17: Provisional AWS Frankfurt estimate excl. email (docs/readiness/hosting-comparison.md)
A18: Share of hosting split evenly per company | B18: 0.3 | F18: Assumption: the rest is split by seats in use
A19: Emails per seat in use / month | B19: 20 | F19: Assumption
A20: Email cost per 1,000 ($) | B20: 0.1 | F20: Amazon SES Frankfurt list price
A21: File storage per seat in use (GB) | B21: 1 | F21: Assumption
A22: Storage cost per GB-month incl. backup copy ($) | B22: 0.05 | F22: Assumption
A23: Compute cost per 1,000 automation runs ($) | B23: 0.05 | F23: Assumption
A24: Share of included runs actually used | B24: 0.5 | F24: Assumption
A25: Support cost per hour, fully loaded ($) | B25: 40 | F25: Owner test value, 20 Oct 2026
A26: Extra support price per hour ($) | B26: 60 | F26: Proposed: sold in 30-minute steps, separate from the plan price
A27: Average customer lifetime (months) | B27: 24 | F27: Assumption: spreads one-off onboarding over the months it serves
A28: Card processing — percent of charge | B28: 0.03 | F28: Typical; varies by processor and country
... A30: Annual price multiple (× monthly) | B30: 10 | F30: Draft, unpublished; approval on hold
A32: Blue = input you can change · yellow = biggest effect on the answer · black = calculated · green = taken from another sheet.

Sheet Pilot subsidy
A1: Pilot subsidy — what the pilot costs Meronatic, and a proposed spending cap
A2: Proposed pilot terms: no ConversaFlow fee; Meta message fees paid by each pilot company directly.
A4: Input | B4: 3 companies | C4: 5 companies | D4: Note
A5: Pilot companies | B5: 3 | C5: 5 | D5: One per sector; up to five if you choose more
A6: Pilot length (days) | B6: 90 | C6: 90 | D6: Same as the system default for a pilot enrolment
A7: Onboarding time per company (hours) | B7: 8 | C7: 8 | D7: Kick-off, workspace set-up, templates, training, closing summary
A8: Weeks of close support | B8: 2 | C8: 2 | D8: From the onboarding plan in the preparation pack
A9: Support hours per week, close support | B9: 4 | C9: 4 | D9: Assumption: daily check-ins plus the weekly review
A10: Support hours per week, afterwards | B10: 1.5 | C10: 1.5 | D10: Assumption: weekly 30-minute review plus questions
A11: Hosting during the pilot ($ / month) | B11: 441 | C11: 441 | D11: Provisional AWS Frankfurt pilot estimate excl. email (production and staging)
A12: Other running costs per company ($ / month) | B12: 5 | C12: 5 | D12: Email, storage, logs: assumption, small
A13: ConversaFlow fee per company during the pilot ($ / month) | B13: 0 | C13: 0 | D13: Proposed pilot terms: no fee
A14: Contingency on top of the estimate | B14: 0.15 | C14: 0.15 | D14: For extra support time or a longer pilot
A15: Support cost per hour ($) | B15: =Assumptions!$B$25 -> 40 | C15: =Assumptions!$B$25 -> 40 | D15: From Assumptions
A17: Calculation | B17: 3 companies | C17: 5 companies | D17: How it is worked out
A18: Pilot length (months) | B18: =B6/30.4 -> 2.9605263 | C18: =C6/30.4 -> 2.9605263 | D18: Days ÷ 30.4
A19: Support hours per company | B19: =B7+B8*B9+MAX(0,B6/7-B8)*B10 -> 32.285714 | C19: =C7+C8*C9+MAX(0,C6/7-C8)*C10 -> 32.285714 | D19: Onboarding + close-support weeks + the remaining weeks
A20: Support time ($) | B20: =B5*B19*B15 -> 3874.2857 | C20: =C5*C19*C15 -> 6457.1429 | D20: Companies × hours × hourly cost
A21: Hosting ($) | B21: =B18*B11 -> 1305.5921 | C21: =C18*C11 -> 1305.5921 | D21: Months × monthly hosting
A22: Other running costs ($) | B22: =B5*B18*B12 -> 44.407895 | C22: =C5*C18*C12 -> 74.013158 | D22: Companies × months × cost
A23: Total cost ($) | B23: =B20+B21+B22 -> 5224.2857 | C23: =C20+C21+C22 -> 7836.7481 | D23: Support + hosting + other
A24: Less pilot fees received ($) | B24: =B5*B18*B13 -> 0 | C24: =C5*C18*C13 -> 0 | D24: Zero under the proposed terms
A25: Pilot subsidy ($) | B25: =B23-B24 -> 5224.2857 | C25: =C23-C24 -> 7836.7481 | D25: What Meronatic pays for the pilot
A26: Proposed spending cap ($) | B26: =CEILING(B25*(1+B14),500) -> 6500 | C26: =CEILING(C25*(1+C14),500) -> 9500 | D26: Subsidy plus contingency, rounded up to the next $500
A28: Not included: the independent security review (quoted separately), legal drafting, Meta fees (paid by the pilot companies) and development time.
A29: Hosting is shared: it is the same whether the pilot has three or five companies, so more companies lower the subsidy per company.
A30: How the cap would work: spending is tracked monthly against the cap; reaching 80% triggers a review with you before more is committed.

Sheet Support offer
A1: Proposed support offer per plan (draft for your decision)
B3: Starter | C3: Growth | D3: Business | E3: Enterprise
A4: Included support each month | B4: 15 minutes by email, next business day | C4: 45 minutes by email and chat, same business day | D4: 3 hours, priority, named contact | E4: 6 hours, priority, named contact
A5: Onboarding | B5: Self-service guide; assisted set-up optional at $99 | C5: Paid onboarding $199, one-off (about 3 hours) | D5: Paid onboarding $399 (about 6 hours) | E5: Paid onboarding from $799 (about 12 hours)
A6: Extra support | B6: $60 per hour, in 30-minute steps | C6: $60 per hour, in 30-minute steps | D6: $60 per hour, in 30-minute steps | E6: Included in the contract or $60 per hour
A7: Help centre and guides | B7: Yes | C7: Yes | D7: Yes | E7: Yes
A8: Annual billing (10 × monthly) | B8: On hold until you approve | C8: On hold until you approve | D8: On hold until you approve | E8: On hold until you approve
A10: All figures are proposals for your decision. Nothing is published or offered to customers.
