Workbook

Sheet Read me
A1: ConversaFlow — annual pricing margin model (draft)
A2: Purpose: show the expected gross margin per plan, on monthly and on annual billing (annual = 10 × monthly), after infrastructure, customer support and the usage included in each plan — before final pricing approval.
A3: Status: draft for margin review. The annual prices are stored unpublished in the system; nothing is offered to customers.
A5: How to use
A6: • Change only the blue numbers on the Assumptions sheet. Yellow marks the assumptions with the biggest effect on margin.
A7: • The Margin sheet recalculates. It shows two scales: a pilot (5 companies) and growth (100 companies).
A9: What is excluded (by owner decision, 19 Oct 2026)
A10: • Meta (WhatsApp) message fees — each customer pays Meta directly.
A11: • Usage overages — billed separately when they occur.
A12: • Not yet modelled: AI costs (Phase 4, to be sold as credits), sales commission, taxes, development cost.
A14: Where the cost figures come from
A15: • Hosting: EU hosting comparison of 19 Oct 2026 (AWS Frankfurt, list prices, estimates; see the Pre-Pilot Preparation Pack). Some AWS Frankfurt prices came from third-party mirrors and should be checked in the AWS calculator.
... A17: • Support time, support cost and included-usage costs: working assumptions, not sourced — replace with your own figures.

Sheet Margin
A1: Growth scale — 100 companies (plan mix on Assumptions)
A2: Plan | B2: Monthly price | C2: Annual price (draft) | D2: Annual, per month | E2: Hosting | F2: Support | G2: Included usage | H2: Card fees (monthly billing) | I2: Card fees (annual, per month) | J2: Margin, monthly billing | K2: Margin %, monthly | L2: Margin, annual billing (per month) | M2: Margin %, annual
A3: Starter | B3: =Assumptions!$B$3 -> 29 | C3: =B3*Assumptions!$B$24 -> 290 | D3: =C3/12 -> 24.166667 | E3: =IF((Assumptions!$B$8+Assumptions!$C$8+Assumptions!$D$8+Assumptions!$E$8)=0,0,Assumptions!$B$12*(Assumptions!$B$16/(Assumptions!$B$8+Assumptions!$C$8+Assumptions!$D$8+Assumptions!$E$8)+(1-Assumptions!$B$16)*Assumptions!$B$4*Assumptions!$B$5/(Assumptions!$B$8*Assumptions!$B$4*Assumptions!$B$5+Assumptions!$C$8*Assumptions!$C$4*Assumptions!$C$5+Assumptions!$D$8*Assumptions!$D$4*Assumptions!$D$5+Assumptions!$E$8*Assumptions!$E$4*Assumptions!$E$5))) -> 7.336918 | F3: =Assumptions!$B$7*Assumptions!$B$21 -> 10 | G3: =Assumptions!$B$4*Assumptions!$B$5*Assumptions!$B$14/1000*Assumptions!$B$15+Assumptions!$B$4*Assumptions!$B$5*Assumptions!$B$17*Assumptions!$B$18+Assumptions!$B$6*Assumptions!$B$20/1000*Assumptions!$B$19 -> 0.1342 | H3: =B3*Assumptions!$B$22+Assumptions!$B$23 -> 1.17 | I3: =(C3*Assumptions!$B$22+Assumptions!$B$23)/12 -> 0.75 | J3: =B3-E3-F3-G3-H3 -> 10.358882 | K3: =IF(B3=0,0,J3/B3) -> 0.35720283 | L3: =D3-E3-F3-G3-I3 -> 5.9455486 | M3: =IF(D3=0,0,L3/D3) -> 0.2460227
A4: Growth | B4: =Assumptions!$C$3 -> 79 | C4: =B4*Assumptions!$B$24 -> 790 | D4: =C4/12 -> 65.833333 | E4: =IF((Assumptions!$B$8+Assumptions!$C$8+Assumptions!$D$8+Assumptions!$E$8)=0,0,Assumptions!$B$12*(Assumptions!$B$16/(Assumptions!$B$8+Assumptions!$C$8+Assumptions!$D$8+Assumptions!$E$8)+(1-Assumptions!$B$16)*Assumptions!$C$4*Assumptions!$C$5/(Assumptions!$B$8*Assumptions!$B$4*Assumptions!$B$5+Assumptions!$C$8*Assumptions!$C$4*Assumptions!$C$5+Assumptions!$D$8*Assumptions!$D$4*Assumptions!$D$5+Assumptions!$E$8*Assumptions!$E$4*Assumptions!$E$5))) -> 13.578393 | F4: =Assumptions!$C$7*Assumptions!$B$21 -> 30 | G4: =Assumptions!$C$4*Assumptions!$C$5*Assumptions!$B$14/1000*Assumptions!$B$15+Assumptions!$C$4*Assumptions!$C$5*Assumptions!$B$17*Assumptions!$B$18+Assumptions!$C$6*Assumptions!$B$20/1000*Assumptions!$B$19 -> 0.489 | H4: =B4*Assumptions!$B$22+Assumptions!$B$23 -> 2.67 | I4: =(C4*Assumptions!$B$22+Assumptions!$B$23)/12 -> 2 | J4: =B4-E4-F4-G4-H4 -> 32.262607 | K4: =IF(B4=0,0,J4/B4) -> 0.40838742 | L4: =D4-E4-F4-G4-I4 -> 19.76594 | M4: =IF(D4=0,0,L4/D4) -> 0.30024212
A5: Business | B5: =Assumptions!$D$3 -> 199 | C5: =B5*Assumptions!$B$24 -> 1990 | D5: =C5/12 -> 165.83333 | E5: =IF((Assumptions!$B$8+Assumptions!$C$8+Assumptions!$D$8+Assumptions!$E$8)=0,0,Assumptions!$B$12*(Assumptions!$B$16/(Assumptions!$B$8+Assumptions!$C$8+Assumptions!$D$8+Assumptions!$E$8)+(1-Assumptions!$B$16)*Assumptions!$D$4*Assumptions!$D$5/(Assumptions!$B$8*Assumptions!$B$4*Assumptions!$B$5+Assumptions!$C$8*Assumptions!$C$4*Assumptions!$C$5+Assumptions!$D$8*Assumptions!$D$4*Assumptions!$D$5+Assumptions!$E$8*Assumptions!$E$4*Assumptions!$E$5))) -> 26.952984 | F5: =Assumptions!$D$7*Assumptions!$B$21 -> 60 | G5: =Assumptions!$D$4*Assumptions!$D$5*Assumptions!$B$14/1000*Assumptions!$B$15+Assumptions!$D$4*Assumptions!$D$5*Assumptions!$B$17*Assumptions!$B$18+Assumptions!$D$6*Assumptions!$B$20/1000*Assumptions!$B$19 -> 1.535 | H5: =B5*Assumptions!$B$22+Assumptions!$B$23 -> 6.27 | I5: =(C5*Assumptions!$B$22+Assumptions!$B$23)/12 -> 5 | J5: =B5-E5-F5-G5-H5 -> 104.24202 | K5: =IF(B5=0,0,J5/B5) -> 0.52382923 | L5: =D5-E5-F5-G5-I5 -> 72.34535 | M5: =IF(D5=0,0,L5/D5) -> 0.43625337
A6: Enterprise | B6: =Assumptions!$E$3 -> 499 | C6: =B6*Assumptions!$B$24 -> 4990 | D6: =C6/12 -> 415.83333 | E6: =IF((Assumptions!$B$8+Assumptions!$C$8+Assumptions!$D$8+Assumptions!$E$8)=0,0,Assumptions!$B$12*(Assumptions!$B$16/(Assumptions!$B$8+Assumptions!$C$8+Assumptions!$D$8+Assumptions!$E$8)+(1-Assumptions!$B$16)*Assumptions!$E$4*Assumptions!$E$5/(Assumptions!$B$8*Assumptions!$B$4*Assumptions!$B$5+Assumptions!$C$8*Assumptions!$C$4*Assumptions!$C$5+Assumptions!$D$8*Assumptions!$D$4*Assumptions!$D$5+Assumptions!$E$8*Assumptions!$E$4*Assumptions!$E$5))) -> 49.243967 | F6: =Assumptions!$E$7*Assumptions!$B$21 -> 120 | G6: =Assumptions!$E$4*Assumptions!$E$5*Assumptions!$B$14/1000*Assumptions!$B$15+Assumptions!$E$4*Assumptions!$E$5*Assumptions!$B$17*Assumptions!$B$18+Assumptions!$E$6*Assumptions!$B$20/1000*Assumptions!$B$19 -> 3.07 | H6: =B6*Assumptions!$B$22+Assumptions!$B$23 -> 15.27 | I6: =(C6*Assumptions!$B$22+Assumptions!$B$23)/12 -> 12.5 | J6: =B6-E6-F6-G6-H6 -> 311.41603 | K6: =IF(B6=0,0,J6/B6) -> 0.62408023 | L6: =D6-E6-F6-G6-I6 -> 231.01937 | M6: =IF(D6=0,0,L6/D6) -> 0.55555759
A7: Whole mix | B7: =Assumptions!$B$8*B3+Assumptions!$C$8*B4+Assumptions!$D$8*B5+Assumptions!$E$8*B6 -> 10400 | D7: =Assumptions!$B$8*D3+Assumptions!$C$8*D4+Assumptions!$D$8*D5+Assumptions!$E$8*D6 -> 8666.6667 | J7: =Assumptions!$B$8*J3+Assumptions!$C$8*J4+Assumptions!$D$8*J5+Assumptions!$E$8*J6 -> 5185.467 | K7: =IF(B7=0,0,J7/B7) -> 0.4986026 | L7: =Assumptions!$B$8*L3+Assumptions!$C$8*L4+Assumptions!$D$8*L5+Assumptions!$E$8*L6 -> 3531.6337 | M7: =IF(D7=0,0,L7/D7) -> 0.40749619
A8: "Whole mix" = monthly totals for all companies at this scale (revenue and gross margin in $, margin as a share of revenue).
A10: Pilot scale — 5 companies (fixed hosting spread over very few companies)
A11: Plan | B11: Monthly price | C11: Annual price (draft) | D11: Annual, per month | E11: Hosting | F11: Support | G11: Included usage | H11: Card fees (monthly billing) | I11: Card fees (annual, per month) | J11: Margin, monthly billing | K11: Margin %, monthly | L11: Margin, annual billing (per month) | M11: Margin %, annual
A12: Starter | B12: =Assumptions!$B$3 -> 29 | C12: =B12*Assumptions!$B$24 -> 290 | D12: =C12/12 -> 24.166667 | E12: =IF((Assumptions!$B$9+Assumptions!$C$9+Assumptions!$D$9+Assumptions!$E$9)=0,0,Assumptions!$B$13*(Assumptions!$B$16/(Assumptions!$B$9+Assumptions!$C$9+Assumptions!$D$9+Assumptions!$E$9)+(1-Assumptions!$B$16)*Assumptions!$B$4*Assumptions!$B$5/(Assumptions!$B$9*Assumptions!$B$4*Assumptions!$B$5+Assumptions!$C$9*Assumptions!$C$4*Assumptions!$C$5+Assumptions!$D$9*Assumptions!$D$4*Assumptions!$D$5+Assumptions!$E$9*Assumptions!$E$4*Assumptions!$E$5))) -> 39.146301 | F12: =Assumptions!$B$7*Assumptions!$B$21 -> 10 | G12: =Assumptions!$B$4*Assumptions!$B$5*Assumptions!$B$14/1000*Assumptions!$B$15+Assumptions!$B$4*Assumptions!$B$5*Assumptions!$B$17*Assumptions!$B$18+Assumptions!$B$6*Assumptions!$B$20/1000*Assumptions!$B$19 -> 0.1342 | H12: =B12*Assumptions!$B$22+Assumptions!$B$23 -> 1.17 | I12: =(C12*Assumptions!$B$22+Assumptions!$B$23)/12 -> 0.75 | J12: =B12-E12-F12-G12-H12 -> -21.450501 | K12: =IF(B12=0,0,J12/B12) -> -0.73967246 | L12: =D12-E12-F12-G12-I12 -> -25.863835 | M12: =IF(D12=0,0,L12/D12) -> -1.0702276
A13: Growth | B13: =Assumptions!$C$3 -> 79 | C13: =B13*Assumptions!$B$24 -> 790 | D13: =C13/12 -> 65.833333 | E13: =IF((Assumptions!$B$9+Assumptions!$C$9+Assumptions!$D$9+Assumptions!$E$9)=0,0,Assumptions!$B$13*(Assumptions!$B$16/(Assumptions!$B$9+Assumptions!$C$9+Assumptions!$D$9+Assumptions!$E$9)+(1-Assumptions!$B$16)*Assumptions!$C$4*Assumptions!$C$5/(Assumptions!$B$9*Assumptions!$B$4*Assumptions!$B$5+Assumptions!$C$9*Assumptions!$C$4*Assumptions!$C$5+Assumptions!$D$9*Assumptions!$D$4*Assumptions!$D$5+Assumptions!$E$9*Assumptions!$E$4*Assumptions!$E$5))) -> 68.747671 | F13: =Assumptions!$C$7*Assumptions!$B$21 -> 30 | G13: =Assumptions!$C$4*Assumptions!$C$5*Assumptions!$B$14/1000*Assumptions!$B$15+Assumptions!$C$4*Assumptions!$C$5*Assumptions!$B$17*Assumptions!$B$18+Assumptions!$C$6*Assumptions!$B$20/1000*Assumptions!$B$19 -> 0.489 | H13: =B13*Assumptions!$B$22+Assumptions!$B$23 -> 2.67 | I13: =(C13*Assumptions!$B$22+Assumptions!$B$23)/12 -> 2 | J13: =B13-E13-F13-G13-H13 -> -22.906671 | K13: =IF(B13=0,0,J13/B13) -> -0.28995786 | L13: =D13-E13-F13-G13-I13 -> -35.403338 | M13: =IF(D13=0,0,L13/D13) -> -0.53777222
A14: Business | B14: =Assumptions!$D$3 -> 199 | C14: =B14*Assumptions!$B$24 -> 1990 | D14: =C14/12 -> 165.83333 | E14: =IF((Assumptions!$B$9+Assumptions!$C$9+Assumptions!$D$9+Assumptions!$E$9)=0,0,Assumptions!$B$13*(Assumptions!$B$16/(Assumptions!$B$9+Assumptions!$C$9+Assumptions!$D$9+Assumptions!$E$9)+(1-Assumptions!$B$16)*Assumptions!$D$4*Assumptions!$D$5/(Assumptions!$B$9*Assumptions!$B$4*Assumptions!$B$5+Assumptions!$C$9*Assumptions!$C$4*Assumptions!$C$5+Assumptions!$D$9*Assumptions!$D$4*Assumptions!$D$5+Assumptions!$E$9*Assumptions!$E$4*Assumptions!$E$5))) -> 132.17918 | F14: =Assumptions!$D$7*Assumptions!$B$21 -> 60 | G14: =Assumptions!$D$4*Assumptions!$D$5*Assumptions!$B$14/1000*Assumptions!$B$15+Assumptions!$D$4*Assumptions!$D$5*Assumptions!$B$17*Assumptions!$B$18+Assumptions!$D$6*Assumptions!$B$20/1000*Assumptions!$B$19 -> 1.535 | H14: =B14*Assumptions!$B$22+Assumptions!$B$23 -> 6.27 | I14: =(C14*Assumptions!$B$22+Assumptions!$B$23)/12 -> 5 | J14: =B14-E14-F14-G14-H14 -> -0.98417808 | K14: =IF(B14=0,0,J14/B14) -> -0.0049456185 | L14: =D14-E14-F14-G14-I14 -> -32.880845 | M14: =IF(D14=0,0,L14/D14) -> -0.19827645
A15: Enterprise | B15: =Assumptions!$E$3 -> 499 | C15: =B15*Assumptions!$B$24 -> 4990 | D15: =C15/12 -> 415.83333 | E15: =IF((Assumptions!$B$9+Assumptions!$C$9+Assumptions!$D$9+Assumptions!$E$9)=0,0,Assumptions!$B$13*(Assumptions!$B$16/(Assumptions!$B$9+Assumptions!$C$9+Assumptions!$D$9+Assumptions!$E$9)+(1-Assumptions!$B$16)*Assumptions!$E$4*Assumptions!$E$5/(Assumptions!$B$9*Assumptions!$B$4*Assumptions!$B$5+Assumptions!$C$9*Assumptions!$C$4*Assumptions!$C$5+Assumptions!$D$9*Assumptions!$D$4*Assumptions!$D$5+Assumptions!$E$9*Assumptions!$E$4*Assumptions!$E$5))) -> 237.89836 | F15: =Assumptions!$E$7*Assumptions!$B$21 -> 120 | G15: =Assumptions!$E$4*Assumptions!$E$5*Assumptions!$B$14/1000*Assumptions!$B$15+Assumptions!$E$4*Assumptions!$E$5*Assumptions!$B$17*Assumptions!$B$18+Assumptions!$E$6*Assumptions!$B$20/1000*Assumptions!$B$19 -> 3.07 | H15: =B15*Assumptions!$B$22+Assumptions!$B$23 -> 15.27 | I15: =(C15*Assumptions!$B$22+Assumptions!$B$23)/12 -> 12.5 | J15: =B15-E15-F15-G15-H15 -> 122.76164 | K15: =IF(B15=0,0,J15/B15) -> 0.24601532 | L15: =D15-E15-F15-G15-I15 -> 42.364977 | M15: =IF(D15=0,0,L15/D15) -> 0.1018797
A16: Whole mix | B16: =Assumptions!$B$9*B12+Assumptions!$C$9*B13+Assumptions!$D$9*B14+Assumptions!$E$9*B15 -> 585 | D16: =Assumptions!$B$9*D12+Assumptions!$C$9*D13+Assumptions!$D$9*D14+Assumptions!$E$9*D15 -> 487.5 | J16: =Assumptions!$B$9*J12+Assumptions!$C$9*J13+Assumptions!$D$9*J14+Assumptions!$E$9*J15 -> -69.2322 | K16: =IF(B16=0,0,J16/B16) -> -0.11834564 | L16: =Assumptions!$B$9*L12+Assumptions!$C$9*L13+Assumptions!$D$9*L14+Assumptions!$E$9*L15 -> -162.4322 | M16: =IF(D16=0,0,L16/D16) -> -0.33319426
A17: "Whole mix" = monthly totals for all companies at this scale (revenue and gross margin in $, margin as a share of revenue).

Sheet Assumptions
A2: Per plan | B2: Starter | C2: Growth | D2: Business | E2: Enterprise | F2: Note / source
A3: Monthly price ($) | B3: 29 | C3: 79 | D3: 199 | E3: 499 | F3: BRD v1.1 proposed prices (owner-approved catalogue, version 1)
A4: Seat limit | B4: 3 | C4: 10 | D4: 25 | E4: 50 | F4: BRD v1.1 plan limits
A5: Share of seats in use | B5: 0.7 | C5: 0.7 | D5: 0.7 | E5: 0.7 | F5: Assumption: companies use 70% of their seat limit
A6: Included automation runs / month | B6: 1000 | C6: 5000 | D6: 25000 | E6: 50000 | F6: BRD v1.1; Enterprise is custom — 50,000 assumed for costing
A7: Support hours per company / month | B7: 0.5 | C7: 1.5 | D7: 3 | E7: 6 | F7: Assumption — replace with your support plan
A8: Companies at growth scale | B8: 40 | C8: 35 | D8: 20 | E8: 5 | F8: Assumption: plan mix of 100 companies
A9: Companies at pilot scale | B9: 1 | C9: 2 | D9: 2 | E9: 0 | F9: Assumption: 5 pilot companies
A11: Shared inputs | B11: Value | F11: Note / source
A12: Hosting at growth scale ($ / month) | B12: 1554 | F12: AWS Frankfurt growth estimate excl. email (docs/readiness/hosting-comparison.md): HA database, app and ClamAV containers, 1 TB files, WAF, backups, logs, support plan
A13: Hosting at pilot scale ($ / month) | B13: 441 | F13: AWS Frankfurt pilot estimate excl. email (docs/readiness/hosting-comparison.md): production + smaller staging
A14: Emails per seat in use / month | B14: 20 | F14: Assumption: invitations, resets, notifications
A15: Email cost per 1,000 ($) | B15: 0.1 | F15: Amazon SES Frankfurt list price
A16: Share of hosting split evenly per company | B16: 0.3 | F16: Assumption: rest is split by seats in use
A17: File storage per seat in use (GB) | B17: 1 | F17: Assumption
A18: Storage cost per GB-month incl. backup copy ($) | B18: 0.05 | F18: Assumption: S3 Frankfurt about $0.0245/GB plus a second-region copy
A19: Compute cost per 1,000 automation runs ($) | B19: 0.05 | F19: Assumption: worker and database time
A20: Share of included runs actually used | B20: 0.5 | F20: Assumption
A21: Support cost per hour, fully loaded ($) | B21: 20 | F21: Assumption — e.g. a GCC-based support agent incl. overheads
A22: Card processing — percent of charge | B22: 0.03 | F22: Typical card fee; varies by processor and country
A23: Card processing — fixed fee per charge ($) | B23: 0.3 | F23: Typical card fee
A24: Annual price multiple (× monthly) | B24: 10 | F24: Owner decision 19 Oct 2026 (draft, unpublished)
A26: Legend: blue = input you can change · yellow = biggest effect on margin · black = calculated.
